addtwo/__init__.py
addtwo/core.py
sajal_addtwo-0.1.0.dist-info/licenses/LICENSE
sajal_addtwo-0.1.0.dist-info/METADATA
sajal_addtwo-0.1.0.dist-info/WHEEL
sajal_addtwo-0.1.0.dist-info/top_level.txt
sajal_addtwo-0.1.0.dist-info/RECORD
